{
    "Members": [
        "name",
        "dodid",
        "homePhone",
        "ssn",
        "dateOfBirth",
        "dateArrivedAtStation",
        "age",
        "personalEmail",
        "militaryEmail",
        "homeAddress",
        "gender",
        "personalTagline",
        "jobtitle",
        "awsS3Link",
        "completeGlideMemberUrl",
        "hasconflict",
        "roles_Fk",
        "jobs_Fk",
        "groups_Fk",
        "squadrons_Fk",
        "members_id",
        "updated_idx"
    ],
    "Requirements": [
        "requirements",
        "members_Fk",
        "appointmenttype_Fk",
        "status",
        "isbooked",
        "requirements_id",
        "updated_idx"
    ],
    "Squadrons": [
        "squadron",
        "supervisorName",
        "squadronReadinessStatus",
        "imageUrl",
        "groups_Fk",
        "squadrons_id",
        "updated_idx"
    ],
    "Groups": [
        "group",
        "supervisorName",
        "groupReadinessStatus",
        "imageUrl",
        "groups_id",
        "updated_idx"
    ],
    "Appointmenttype": [
        "name",
        "durationMinutes",
        "appointmenttype_id",
        "updated_idx"
    ],
    "RifleTraining": [
        "member",
        "completedDate",
        "expirationDate",
        "status",
        "members_Fk",
        "rifletraining_id",
        "updated_idx"
    ],
    "M249Training": [
        "member",
        "completedDate",
        "expirationDate",
        "status",
        "members_Fk",
        "m249Training_id",
        "updated_idx"
    ],
    "M4Training": [
        "member",
        "completedDate",
        "expirationDate",
        "status",
        "members_Fk",
        "m4Training_id",
        "updated_idx"
    ],
    "GrenadeTraining": [
        "member",
        "completedDate",
        "expirationDate",
        "status",
        "members_Fk",
        "grenadetraining_id",
        "updated_idx"
    ],
    "M240Training": [
        "member",
        "completedDate",
        "expirationDate",
        "status",
        "members_Fk",
        "m240Training_id",
        "updated_idx"
    ],
    "Roles": [
        "roleTitle",
        "roleDescription",
        "roles_id",
        "updated_idx"
    ],
    "Jobs": [
        "jobTitle",
        "description",
        "squadrons_Fk",
        "jobs_id",
        "updated_idx"
    ],
    "VehicleEquipment": [
        "name",
        "description",
        "model",
        "manufacturer",
        "serialnumber",
        "acquisitionDate",
        "condition",
        "lastMaintenanceDate",
        "nextMaintenanceDate",
        "vehicleequipment_id",
        "updated_idx"
    ],
    "MaintenanceEquipment": [
        "name",
        "description",
        "model",
        "manufacturer",
        "serialNumber",
        "acquisitionDate",
        "condition",
        "lastMaintenanceDate",
        "nextMaintenanceDate",
        "maintenanceequipment_id",
        "updated_idx"
    ],
    "CommunicationsEquipment": [
        "name",
        "description",
        "model",
        "manufacturer",
        "serialNumber",
        "acquisitionDate",
        "condition",
        "lastMaintenanceDate",
        "nextMaintenanceDate",
        "communicationsequipment_id",
        "updated_idx"
    ],
    "AircraftEquipment": [
        "name",
        "description",
        "model",
        "manufacturer",
        "serialNumber",
        "acquisitionDate",
        "condition",
        "lastMaintenanceDate",
        "nextMaintenanceDate",
        "aircraftequipment_id",
        "updated_idx"
    ],
    "Slots": [
        "slotId",
        "startTime",
        "endTime",
        "slotcapacity",
        "slotused",
        "isbooked",
        "appointmenttype_Fk",
        "members_Fk",
        "slots_id",
        "updated_idx"
    ],
    "Skills": [
        "skill",
        "source",
        "type",
        "skills_id",
        "updated_idx"
    ]
}